{
  "string": [
    {
      "name": "module_desc",
      "value": "MiTu 的 UI 部分, 用于整合 picture_search 和 picture_bed, 并将结果展示出来"
    },
    {
      "name": "soutu",
      "value": "搜图"
    },
    {
      "name": "album",
      "value": "相册"
    },
    {
      "name": "repo",
      "value": "仓库"
    },
    {
      "name": "setting",
      "value": "设置"
    },
    {
      "name": "other",
      "value": "其它"
    },
    {
      "name": "quit",
      "value": "退出"
    },
    {
      "name": "about",
      "value": "关于"
    },
    {
      "name": "group",
      "value": "分组"
    },
    {
      "name": "system",
      "value": "跟随系统"
    },
    {
      "name": "light",
      "value": "亮色主题"
    },
    {
      "name": "dark",
      "value": "暗色主题"
    },
    {
      "name": "source",
      "value": "源"
    },
    {
      "name": "img_source",
      "value": "图源"
    },
    {
      "name": "bed_source",
      "value": "图床源"
    },
    {
      "name": "no_set_rule",
      "value": "暂未设置规则"
    },
    {
      "name": "search_placeholder",
      "value": "搜索图片名, 描述"
    },
    {
      "name": "img_source_manage",
      "value": "图源管理"
    },
    {
      "name": "img_source_manage_sub",
      "value": "新建、导入、编辑或删除图源"
    },
    {
      "name": "bed_source_manage",
      "value": "图床源管理"
    },
    {
      "name": "bed_source_manage_sub",
      "value": "新建、导入、编辑或删除图床源"
    },
    {
      "name": "multi_group",
      "value": "多分组/图源"
    },
    {
      "name": "switch_img_source",
      "value": "切换图源"
    },
    {
      "name": "search_history",
      "value": "搜索历史"
    },
    {
      "name": "clear",
      "value": "清除"
    },
    {
      "name": "cancel",
      "value": "取消"
    },
    {
      "name": "confirm",
      "value": "确认"
    },
    {
      "name": "select_all",
      "value": "全选"
    },
    {
      "name": "not_select_all",
      "value": "全不选"
    },
    {
      "name": "backup_setting",
      "value": "备份设置"
    },
    {
      "name": "backup_setting_sub",
      "value": "WebDav 设置/导入数据"
    },
    {
      "name": "theme_setting",
      "value": "主题设置"
    },
    {
      "name": "theme_setting_sub",
      "value": "与界面颜色相关的一些设置"
    },
    {
      "name": "theme_mode",
      "value": "主题模式"
    },
    {
      "name": "theme_mode_sub",
      "value": "选择主题模式"
    },
    {
      "name": "other_setting",
      "value": "其它设置"
    },
    {
      "name": "other_setting_sub",
      "value": "与功能相关的一些设置"
    },
    {
      "name": "about_page_share",
      "value": "MiTu 下载地址"
    },
    {
      "name": "developer",
      "value": "开发人员"
    },
    {
      "name": "developer_sub",
      "value": "详情请在 GitHub 中查看"
    },
    {
      "name": "update_log",
      "value": "更新日志"
    },
    {
      "name": "version_param",
      "value": "版本 %s"
    },
    {
      "name": "check_update",
      "value": "检查更新"
    }
  ]
}